goose_mentor_mode/__init__.py
goose_mentor_mode/__main__.py
goose_mentor_mode/mentor_engine.py
goose_mentor_mode/mentor_toolkit.py
goose_mentor_mode/py.typed
goose_mentor_mode/server.py
goose_mentor_mode-0.1.6.dist-info/METADATA
goose_mentor_mode-0.1.6.dist-info/WHEEL
goose_mentor_mode-0.1.6.dist-info/entry_points.txt
goose_mentor_mode-0.1.6.dist-info/licenses/LICENSE
goose_mentor_mode-0.1.6.dist-info/RECORD
