Metadata-Version: 2.4
Name: goose-mentor-mode
Version: 0.1.6
Summary: AI-powered mentor extension for Goose that transforms automation into guided learning
Project-URL: Homepage, https://github.com/joeeuston-dev/goose-mentor-mode
Project-URL: Repository, https://github.com/joeeuston-dev/goose-mentor-mode
Project-URL: Documentation, https://github.com/joeeuston-dev/goose-mentor-mode/blob/main/README.md
Project-URL: Issues, https://github.com/joeeuston-dev/goose-mentor-mode/issues
Author-email: Joe Euston <joe@example.com>
License: MIT
License-File: LICENSE
Keywords: ai,development,goose,learning,mcp,mentor
Classifier: Development Status :: 4 - Beta
Classifier: Intended Audience :: Developers
Classifier: License :: OSI Approved :: MIT License
Classifier: Programming Language :: Python :: 3
Classifier: Programming Language :: Python :: 3.11
Classifier: Programming Language :: Python :: 3.12
Classifier: Topic :: Education
Classifier: Topic :: Software Development :: Libraries :: Python Modules
Requires-Python: >=3.11
Requires-Dist: mcp[cli]>=1.2.0
Requires-Dist: typing-extensions>=4.0.0
Provides-Extra: dev
Requires-Dist: black>=23.0.0; extra == 'dev'
Requires-Dist: mypy>=1.5.0; extra == 'dev'
Requires-Dist: pytest-asyncio>=0.21.0; extra == 'dev'
Requires-Dist: pytest>=7.0.0; extra == 'dev'
Requires-Dist: ruff>=0.1.0; extra == 'dev'
